wsl_pathlib/__init__.py
wsl_pathlib/path.py
wsl_pathlib/py.typed
wsl_pathlib-0.1.4.dist-info/LICENSE
wsl_pathlib-0.1.4.dist-info/METADATA
wsl_pathlib-0.1.4.dist-info/WHEEL
wsl_pathlib-0.1.4.dist-info/RECORD
